rara_tools/converters.py
rara_tools/decorators.py
rara_tools/digar_schema_converter.py
rara_tools/elastic.py
rara_tools/exceptions.py
rara_tools/s3.py
rara_tools/task_reporter.py
rara_tools/utils.py
rara_tools/constants/__init__.py
rara_tools/constants/digitizer.py
rara_tools/constants/general.py
rara_tools/constants/language_evaluator.py
rara_tools/constants/linker.py
rara_tools/constants/meta_extractor.py
rara_tools/constants/normalizers.py
rara_tools/constants/parsers.py
rara_tools/constants/subject_indexer.py
rara_tools/core_formatters/core_formatter.py
rara_tools/core_formatters/formatted_keyword.py
rara_tools/core_formatters/formatted_meta.py
rara_tools/core_formatters/formatted_object.py
rara_tools/normalizers/__init__.py
rara_tools/normalizers/authorities.py
rara_tools/normalizers/base.py
rara_tools/normalizers/bibs.py
rara_tools/normalizers/exceptions.py
rara_tools/normalizers/reader.py
rara_tools/normalizers/viaf.py
rara_tools/parsers/mets_alto_parser.py
rara_tools/parsers/marc_parsers/base_parser.py
rara_tools/parsers/marc_parsers/ems_parser.py
rara_tools/parsers/marc_parsers/location_parser.py
rara_tools/parsers/marc_parsers/organization_parser.py
rara_tools/parsers/marc_parsers/person_parser.py
rara_tools/parsers/marc_parsers/title_parser.py
rara_tools/parsers/marc_records/base_record.py
rara_tools/parsers/marc_records/ems_record.py
rara_tools/parsers/marc_records/organization_record.py
rara_tools/parsers/marc_records/person_record.py
rara_tools/parsers/marc_records/title_record.py
rara_tools/parsers/mets_alto_parsers/author.py
rara_tools/parsers/mets_alto_parsers/keywords.py
rara_tools/parsers/mets_alto_parsers/mets_alto_parser.py
rara_tools/parsers/mets_alto_parsers/title.py
rara_tools/parsers/tools/entity_normalizers.py
rara_tools/parsers/tools/marc_converter.py
rara_tools/parsers/tools/russian_transliterator.py
rara_tools/parsers/tools/validators.py
rara_tools-0.9.1.dist-info/licenses/LICENSE.md
rara_tools-0.9.1.dist-info/METADATA
rara_tools-0.9.1.dist-info/WHEEL
rara_tools-0.9.1.dist-info/top_level.txt
rara_tools-0.9.1.dist-info/RECORD
