Metadata-Version: 2.4
Name: rara-tools
Version: 0.9.1
Summary: Tools to support Kata's work.
Classifier: Programming Language :: Python :: 3
Classifier: Programming Language :: Python :: 3.10
Classifier: Programming Language :: Python :: 3.11
Classifier: Programming Language :: Python :: 3.12
Classifier: Intended Audience :: Science/Research
Requires-Python: >=3.10
License-File: LICENSE.md
Requires-Dist: elasticsearch==8.*
Requires-Dist: elasticsearch_dsl==8.*
Requires-Dist: minio==7.2.16
Requires-Dist: estnltk==1.7.3
Requires-Dist: nltk
Requires-Dist: jsonlines
Requires-Dist: requests
Requires-Dist: iso639-lang
Requires-Dist: jellyfish
Requires-Dist: pymarc
Requires-Dist: regex
Requires-Dist: glom
Requires-Dist: beautifulsoup4
Provides-Extra: testing
Requires-Dist: pytest>=8.0; extra == "testing"
Requires-Dist: pytest-order; extra == "testing"
Dynamic: license-file
